elapsedtimer.py
elapsedtimer-1.0.0.dist-info/LICENSE
elapsedtimer-1.0.0.dist-info/METADATA
elapsedtimer-1.0.0.dist-info/WHEEL
elapsedtimer-1.0.0.dist-info/top_level.txt
elapsedtimer-1.0.0.dist-info/zip-safe
elapsedtimer-1.0.0.dist-info/RECORD
