Metadata-Version: 2.1
Name: elapsedtimer
Version: 1.0.0
Summary: Elapsed timer and utilities
Home-page: https://github.com/flit/elapsedtimer
Maintainer: Chris Reed
Maintainer-email: flit@me.com
License: BSD 3-Clause
Project-URL: Website, https://github.com/flit/elapsedtimer
Project-URL: Documentation, https://github.com/flit/elapsedtimer
Project-URL: Source, https://github.com/flit/elapsedtimer
Keywords: time,performance,optimize,utility
Platform: UNKNOWN
Classifier: Development Status :: 5 - Production/Stable
Classifier: Environment :: Console
Classifier: Intended Audience :: Developers
Classifier: License :: OSI Approved :: BSD License
Classifier: Operating System :: OS Independent
Classifier: Programming Language :: Python
Classifier: Programming Language :: Python :: 3
Classifier: Programming Language :: Python :: 3.6
Classifier: Programming Language :: Python :: 3.7
Classifier: Programming Language :: Python :: 3.8
Classifier: Programming Language :: Python :: 3.9
Classifier: Programming Language :: Python :: 3.10
Classifier: Topic :: Software Development
Classifier: Topic :: Software Development :: Libraries
Classifier: Topic :: Software Development :: Libraries :: Python Modules
Classifier: Topic :: Software Development :: Testing
Classifier: Topic :: Utilities
Requires-Python: >=3.6.0
License-File: LICENSE
Provides-Extra: test
Requires-Dist: pytest (>=6.2) ; extra == 'test'
Requires-Dist: flake8 (>=4.0) ; extra == 'test'
